[
{"Province_State":"Alabama","Population":"4903185"},
{"Province_State":"Alaska","Population":"731545"},
{"Province_State":"Arizona","Population":"7278717"},
{"Province_State":"Arkansas","Population":"3017825"},
{"Province_State":"California","Population":"39512223"},
{"Province_State":"Colorado","Population":"5758736"},
{"Province_State":"Connecticut","Population":"3565287"},
{"Province_State":"Delaware","Population":"973764"},
{"Province_State":"District of Columbia","Population":"705749"},
{"Province_State":"Florida","Population":"21477737"},
{"Province_State":"Georgia","Population":"10617423"},
{"Province_State":"Hawaii","Population":"1415872"},
{"Province_State":"Idaho","Population":"1787065"},
{"Province_State":"Illinois","Population":"12671821"},
{"Province_State":"Indiana","Population":"6732219"},
{"Province_State":"Iowa","Population":"3155070"},
{"Province_State":"Kansas","Population":"2913314"},
{"Province_State":"Kentucky","Population":"4467673"},
{"Province_State":"Louisiana","Population":"4648794"},
{"Province_State":"Maine","Population":"1344212"},
{"Province_State":"Maryland","Population":"6045680"},
{"Province_State":"Massachusetts","Population":"6949503"},
{"Province_State":"Michigan","Population":"9986857"},
{"Province_State":"Minnesota","Population":"5639632"},
{"Province_State":"Mississippi","Population":"2976149"},
{"Province_State":"Missouri","Population":"6137428"},
{"Province_State":"Montana","Population":"1068778"},
{"Province_State":"Nebraska","Population":"1934408"},
{"Province_State":"Nevada","Population":"3080156"},
{"Province_State":"New Hampshire","Population":"1359711"},
{"Province_State":"New Jersey","Population":"8882190"},
{"Province_State":"New Mexico","Population":"2096829"},
{"Province_State":"New York","Population":"19453561"},
{"Province_State":"North Carolina","Population":"10488084"},
{"Province_State":"North Dakota","Population":"762062"},
{"Province_State":"Ohio","Population":"11689100"},
{"Province_State":"Oklahoma","Population":"3956971"},
{"Province_State":"Oregon","Population":"4217737"},
{"Province_State":"Pennsylvania","Population":"12801989"},
{"Province_State":"Rhode Island","Population":"1059361"},
{"Province_State":"South Carolina","Population":"5148714"},
{"Province_State":"South Dakota","Population":"884659"},
{"Province_State":"Tennessee","Population":"6833174"},
{"Province_State":"Texas","Population":"28995881"},
{"Province_State":"Utah","Population":"3205958"},
{"Province_State":"Vermont","Population":"623989"},
{"Province_State":"Virginia","Population":"8535519"},
{"Province_State":"Washington","Population":"7614893"},
{"Province_State":"West Virginia","Population":"1792147"},
{"Province_State":"Wisconsin","Population":"5822434"},
{"Province_State":"Wyoming","Population":"578759"},
{"Province_State":"American Samoa","Population":"55641"},
{"Province_State":"Guam","Population":"165718"},
{"Province_State":"Northern Mariana Islands","Population":"55194"},
{"Province_State":"Puerto Rico","Population":"3193694"},
{"Province_State":"Virgin Islands","Population":"104914"}
]
